insightmars/__init__.py
insightmars/utils.py
insight_api-0.5.dist-info/METADATA
insight_api-0.5.dist-info/WHEEL
insight_api-0.5.dist-info/top_level.txt
insight_api-0.5.dist-info/RECORD
