Metadata-Version: 2.1
Name: insight-api
Version: 0.5
Summary: InSight Mars Mission Raw Photo API Wrapper
Home-page: http://github.com/konradit/insight-api
Author: Konrad Iturbe
Author-email: mail@chernowii.com
License: UNKNOWN
Platform: UNKNOWN
